django_gauth/__init__.py
django_gauth/_checks.py
django_gauth/admin.py
django_gauth/apps.py
django_gauth/defaults.py
django_gauth/py.typed
django_gauth/urls.py
django_gauth/utilities.py
django_gauth/views.py
django_gauth/static/django_gauth/office_logo.png
django_gauth/static/django_gauth/user.png
django_gauth/templates/django_gauth/index.html
django_gauth-0.2.0.dist-info/licenses/LICENSE
django_gauth-0.2.0.dist-info/METADATA
django_gauth-0.2.0.dist-info/WHEEL
django_gauth-0.2.0.dist-info/top_level.txt
django_gauth-0.2.0.dist-info/RECORD
