Metadata-Version: 2.4
Name: django_gauth
Version: 0.2.0
Summary: A Django app for providing the Google's discovery based Oauth2 authentication mechanism is HTTP/HTTPS oriented Django Servers/Projects.
Author-email: Ankit Kumar <ankit.kumar05@telusdigital.com>, Ankit Yadav <ankit8290@gmail.com>
Maintainer-email: Ankit yadav <ankit8290@gmail.com>
License: MIT License
Project-URL: Documentation, https://masterpiece93.github.io/django-gauth/
Project-URL: Repository, https://github.com/masterPiece93/django-gauth
Project-URL: Changelog, https://github.com/masterPiece93/django-gauth/releases
Keywords: django_gauth,google,oauth2,auth
Classifier: Development Status :: 5 - Production/Stable
Classifier: Environment :: Web Environment
Classifier: Framework :: Django
Classifier: Framework :: Django :: 3.1
Classifier: Framework :: Django :: 3.2
Classifier: Framework :: Django :: 4.0
Classifier: Framework :: Django :: 4.1
Classifier: Framework :: Django :: 4.2
Classifier: Framework :: Django :: 5.0
Classifier: Framework :: Django :: 5.1
Classifier: Framework :: Django :: 5.2
Classifier: Intended Audience :: Developers
Classifier: License :: OSI Approved :: MIT License
Classifier: Operating System :: OS Independent
Classifier: Programming Language :: Python :: 3 :: Only
Classifier: Programming Language :: Python :: 3.9
Classifier: Programming Language :: Python :: 3.10
Classifier: Programming Language :: Python :: 3.11
Classifier: Programming Language :: Python :: 3.12
Classifier: Programming Language :: Python :: Implementation :: CPython
Classifier: Topic :: Software Development :: Libraries :: Application Frameworks
Classifier: Topic :: Software Development :: Libraries :: Python Modules
Classifier: Topic :: Internet :: WWW/HTTP
Classifier: Topic :: Internet :: WWW/HTTP :: Dynamic Content
Classifier: Topic :: Utilities
Classifier: Typing :: Typed
Requires-Python: >=3.9
License-File: LICENSE
Requires-Dist: google-auth-oauthlib
Requires-Dist: Django>=3.1; python_version >= "3.9" and python_version < "3.11"
Requires-Dist: Django>=4.2.26; python_version >= "3.9"
Provides-Extra: dev
Requires-Dist: build==1.2.1; extra == "dev"
Requires-Dist: nox==2024.4.15; extra == "dev"
Requires-Dist: twine==5.1.1; extra == "dev"
Requires-Dist: check-wheel-contents; extra == "dev"
Requires-Dist: mypy; extra == "dev"
Requires-Dist: graphviz; extra == "dev"
Requires-Dist: pipdeptree; extra == "dev"
Provides-Extra: lint
Requires-Dist: codespell>=2.2.4; extra == "lint"
Requires-Dist: ruff; extra == "lint"
Requires-Dist: vulture; extra == "lint"
Requires-Dist: tomli; extra == "lint"
Requires-Dist: validate-pyproject[all]; extra == "lint"
Requires-Dist: isort; extra == "lint"
Requires-Dist: black; extra == "lint"
Requires-Dist: mypy; extra == "lint"
Requires-Dist: pylint; extra == "lint"
Requires-Dist: pylint-actions; extra == "lint"
Dynamic: license-file
